{
  "books": [
    {
      "title": "Mahabharata",
      "author": "Vyasa",
      "price": 500,
      "description": "Epic battle of Kurukshetra unfolds",
      "imgUrl": "/assets/img3.png",
      "quantity": 12,
      "id": "5dad"
    },
    {
      "title": "Ramayana",
      "author": "Valmiki",
      "price": 600,
      "description": "Rama’s journey to rescue Sita",
      "imgUrl": "/assets/img3.png",
      "quantity": 15,
      "id": "5254"
    },
    {
      "title": "Bhagavad Gita",
      "author": "Vyasa",
      "price": 700,
      "imgUrl": "/assets/img3.png",
      "description": "Krishna imparts wisdom to Arjuna",
      "quantity": 8,
      "id": "1e09"
    },
    {
      "title": "Upanishads",
      "author": "Various",
      "price": 800,
      "imgUrl": "/assets/img3.png",
      "description": "Philosophical texts exploring ultimate reality",
      "quantity": 5,
      "id": "99a9"
    },
    {
      "title": "Vedas",
      "author": "Various",
      "price": 900,
      "imgUrl": "/assets/img3.png",
      "description": "Ancient hymns and spiritual knowledge",
      "quantity": 0,
      "id": "1c1d"
    },
    {
      "title": "Puranas",
      "author": "Various",
      "price": 1000,
      "imgUrl": "/assets/img3.png",
      "description": "Mythological texts narrating the history of the universe",
      "quantity": 0,
      "id": "76fb"
    },
    {
      "id": "01db",
      "title": "asdaas",
      "author": "as",
      "description": "a",
      "price": 12,
      "quantity": 1212,
      "imgUrl": "/assets/img3.png"
    },
    {
      "id": "c60c",
      "title": "hj",
      "author": "k",
      "description": "k",
      "price": 23,
      "quantity": 0,
      "imgUrl": "/assets/img3.png"
    },
    {
      "id": "7427",
      "title": "admin",
      "author": "admin",
      "description": "test",
      "price": 1200,
      "quantity": 0,
      "imgUrl": "/assets/img3.png"
    },
    {
      "id": "20a3",
      "title": "test",
      "author": "test",
      "description": "test",
      "price": 123,
      "quantity": 12,
      "imgUrl": "/assets/img3.png"
    }
  ]
}